{
    "info": {
        "_postman_id": "409648ca-273e-449e-a81b-59cd8d74a31a",
        "name": "Laravel",
        "schema": "https://schema.getpostman.com/json/collection/v2.1.0/collection.json"
    },
    "variable": [
        {
            "key": "local",
            "value": "http://127.0.0.1:8000/api/v1"
        },
        {
            "key": "token",
            "value": ""
        }
    ],
    "event": [
        {
            "listen": "prerequest",
            "script": {
                "type": "text/javascript",
                "exec": [
                    ""
                ]
            }
        }
    ],
    "item": [
        {
            "name": "filling",
            "item": [
                {
                    "name": "get all filling",
                    "protocolProfileBehavior": {
                        "disableBodyPruning": true
                    },
                    "request": {
                        "auth": {
                            "type": "bearer",
                            "bearer": [
                                {
                                    "key": "token",
                                    "value": "{{token}}",
                                    "type": "string"
                                }
                            ]
                        },
                        "method": "GET",
                        "header": [
                            {
                                "key": "Accept",
                                "value": "application/json",
                                "type": "text"
                            }
                        ],
                        "body": {
                            "mode": "formdata",
                            "formdata": [
                                {
                                    "key": "lang",
                                    "description": "For Return Language Message default Arabic",
                                    "type": "text",
                                    "value": "ar"
                                }
                            ]
                        },
                        "url": {
                            "raw": "{{local}}/filling",
                            "host": [
                                "{{local}}"
                            ],
                            "path": [
                                "filling"
                            ]
                        },
                        "description": "test description"
                    },
                    "response": []
                },
                {
                    "name": "show by id filling",
                    "protocolProfileBehavior": {
                        "disableBodyPruning": true
                    },
                    "request": {
                        "auth": {
                            "type": "bearer",
                            "bearer": [
                                {
                                    "key": "token",
                                    "value": "{{token}}",
                                    "type": "string"
                                }
                            ]
                        },
                        "method": "GET",
                        "header": [
                            {
                                "key": "Accept",
                                "value": "application/json",
                                "type": "text"
                            }
                        ],
                        "body": {
                            "mode": "formdata",
                            "formdata": [
                                {
                                    "key": "lang",
                                    "description": "For Return Language Message default Arabic",
                                    "type": "text",
                                    "value": "ar"
                                }
                            ]
                        },
                        "url": {
                            "raw": "{{local}}/filling/{PUT_YOUR_ID}",
                            "host": [
                                "{{local}}"
                            ],
                            "path": [
                                "filling",
                                "{PUT_YOUR_ID}"
                            ]
                        },
                        "description": "test description"
                    },
                    "response": []
                },
                {
                    "name": "Add Record filling",
                    "protocolProfileBehavior": {
                        "disableBodyPruning": true
                    },
                    "request": {
                        "auth": {
                            "type": "bearer",
                            "bearer": [
                                {
                                    "key": "token",
                                    "value": "{{token}}",
                                    "type": "string"
                                }
                            ]
                        },
                        "method": "POST",
                        "header": [
                            {
                                "key": "Accept",
                                "value": "application/json",
                                "type": "text"
                            }
                        ],
                        "body": {
                            "mode": "formdata",
                            "formdata": [
                                {
                                    "key": "lang",
                                    "description": "For Return Language Message default Arabic",
                                    "type": "text",
                                    "value": "ar"
                                },
                                {
                                    "key": "quantity",
                                    "value": "some string",
                                    "type": "text",
                                    "description": "normal input text"
                                },
                                {
                                    "key": "price",
                                    "value": "some string",
                                    "type": "text",
                                    "description": "normal input text"
                                },
                                {
                                    "key": "supplier_id",
                                    "value": "App\\Models\\Supplier::pluck('name'",
                                    "type": "text",
                                    "description": "Dropdown data (App\\Models\\Supplier::pluck('name')"
                                },
                                {
                                    "key": "filling_date",
                                    "value": "some string",
                                    "type": "text",
                                    "description": "normal input text"
                                },
                                {
                                    "key": "note",
                                    "value": "some string",
                                    "type": "text",
                                    "description": "normal input text"
                                }
                            ]
                        },
                        "url": {
                            "raw": "{{local}}/filling",
                            "host": [
                                "{{local}}"
                            ],
                            "path": [
                                "filling"
                            ]
                        },
                        "description": "test description"
                    },
                    "response": []
                },
                {
                    "name": "Update Record By ID filling",
                    "protocolProfileBehavior": {
                        "disableBodyPruning": true
                    },
                    "request": {
                        "auth": {
                            "type": "bearer",
                            "bearer": [
                                {
                                    "key": "token",
                                    "value": "{{token}}",
                                    "type": "string"
                                }
                            ]
                        },
                        "method": "PUT",
                        "header": [
                            {
                                "key": "Accept",
                                "value": "application/json",
                                "type": "text"
                            }
                        ],
                        "body": {
                            "mode": "formdata",
                            "formdata": [
                                {
                                    "key": "lang",
                                    "description": "For Return Language Message default Arabic",
                                    "type": "text",
                                    "value": "ar"
                                },
                                {
                                    "key": "quantity",
                                    "value": "some string",
                                    "type": "text",
                                    "description": "normal input text"
                                },
                                {
                                    "key": "price",
                                    "value": "some string",
                                    "type": "text",
                                    "description": "normal input text"
                                },
                                {
                                    "key": "supplier_id",
                                    "value": "App\\Models\\Supplier::pluck('name'",
                                    "type": "text",
                                    "description": "Dropdown data (App\\Models\\Supplier::pluck('name')"
                                },
                                {
                                    "key": "filling_date",
                                    "value": "some string",
                                    "type": "text",
                                    "description": "normal input text"
                                },
                                {
                                    "key": "note",
                                    "value": "some string",
                                    "type": "text",
                                    "description": "normal input text"
                                }
                            ]
                        },
                        "url": {
                            "raw": "{{local}}/filling/{PUT_YOUR_ID}",
                            "host": [
                                "{{local}}"
                            ],
                            "path": [
                                "filling",
                                "{PUT_YOUR_ID}"
                            ]
                        },
                        "description": "test description"
                    },
                    "response": []
                },
                {
                    "name": "DELETE Record By ID filling",
                    "protocolProfileBehavior": {
                        "disableBodyPruning": true
                    },
                    "request": {
                        "auth": {
                            "type": "bearer",
                            "bearer": [
                                {
                                    "key": "token",
                                    "value": "{{token}}",
                                    "type": "string"
                                }
                            ]
                        },
                        "method": "DELETE",
                        "header": [
                            {
                                "key": "Accept",
                                "value": "application/json",
                                "type": "text"
                            }
                        ],
                        "body": {
                            "mode": "formdata",
                            "formdata": [
                                {
                                    "key": "lang",
                                    "description": "For Return Language Message default Arabic",
                                    "type": "text",
                                    "value": "ar"
                                }
                            ]
                        },
                        "url": {
                            "raw": "{{local}}/filling/{PUT_YOUR_ID}",
                            "host": [
                                "{{local}}"
                            ],
                            "path": [
                                "filling",
                                "{PUT_YOUR_ID}"
                            ]
                        },
                        "description": "test description"
                    },
                    "response": []
                },
                {
                    "name": "Multi Delete Record By IDs filling",
                    "protocolProfileBehavior": {
                        "disableBodyPruning": true
                    },
                    "request": {
                        "auth": {
                            "type": "bearer",
                            "bearer": [
                                {
                                    "key": "token",
                                    "value": "{{token}}",
                                    "type": "string"
                                }
                            ]
                        },
                        "method": "POST",
                        "header": [
                            {
                                "key": "Accept",
                                "value": "application/json",
                                "type": "text"
                            }
                        ],
                        "body": {
                            "mode": "formdata",
                            "formdata": [
                                {
                                    "key": "lang",
                                    "description": "For Return Language Message default Arabic",
                                    "type": "text",
                                    "value": "ar"
                                },
                                {
                                    "key": "selected_data[]",
                                    "value": "1",
                                    "type": "text",
                                    "description": "Record ID Integer"
                                },
                                {
                                    "key": "selected_data[]",
                                    "value": "2",
                                    "type": "text",
                                    "description": "Record ID Integer"
                                }
                            ]
                        },
                        "url": {
                            "raw": "{{local}}/filling/multi_delete",
                            "host": [
                                "{{local}}"
                            ],
                            "path": [
                                "filling",
                                "multi_delete"
                            ]
                        },
                        "description": "test description"
                    },
                    "response": []
                }
            ]
        }
    ]
}